znh5md/__init__.py
znh5md/ase_plugin.py
znh5md/cli.py
znh5md/misc.py
znh5md/znh5md.py
znh5md/interface/__init__.py
znh5md/interface/io.py
znh5md/interface/read.py
znh5md/interface/write.py
znh5md/path/__init__.py
znh5md/serialization/__init__.py
znh5md/serialization/base.py
znh5md/units/__init__.py
znh5md-0.4.8.dist-info/METADATA
znh5md-0.4.8.dist-info/WHEEL
znh5md-0.4.8.dist-info/entry_points.txt
znh5md-0.4.8.dist-info/licenses/LICENSE
znh5md-0.4.8.dist-info/RECORD
