Metadata-Version: 2.4
Name: znh5md
Version: 0.4.8
Summary: ASE Interface for the H5MD format.
Project-URL: Repository, https://github.com/zincware/ZnH5MD
Project-URL: Releases, https://github.com/zincware/ZnH5MD/releases
Project-URL: Discord, https://discord.gg/7ncfwhsnm4
Author-email: Fabian Zills <fzills@icp.uni-stuttgart.de>
License-Expression: Apache-2.0
License-File: LICENSE
Requires-Python: >=3.10
Requires-Dist: ase>=3.24.0
Requires-Dist: h5py>=3.12.1
Requires-Dist: tqdm>=4.67.1
Requires-Dist: typer>=0.15.1
